Oscarscrapper_package/Oscarscrapper.py
Oscarscrapper_package/__init__.py
Oscarscrapper_package/data/corrections/list_films_right.csv
Oscarscrapper_package/data/corrections/list_films_wrong.csv
Oscarscrapper_package/data/corrections/list_names_right.csv
Oscarscrapper_package/data/corrections/list_names_wrong.csv
Oscarscrapper_package/data/corrections/wfdf.csv
OscarScrapper-1.5.dist-info/LICENSE.txt
OscarScrapper-1.5.dist-info/METADATA
OscarScrapper-1.5.dist-info/WHEEL
OscarScrapper-1.5.dist-info/top_level.txt
OscarScrapper-1.5.dist-info/RECORD
