Metadata-Version: 2.1
Name: OscarScrapper
Version: 1.5
Summary: Academy Awards Scraper and Data processor
Home-page: https://github.com/omasamo/Final-Project-JEM207
Author: Yann Aubineau, Samuel Bozon
Author-email: yann.aubineau@gmail.com, samuel.bozon@outlook.com
License: UNKNOWN
Platform: UNKNOWN
License-File: LICENSE.txt
Requires-Dist: markdown
Requires-Dist: requests
Requires-Dist: tdqm
Requires-Dist: scrapy
Requires-Dist: pandas
Requires-Dist: numpy
Requires-Dist: jellyfish
